i_like_frog/__init__.py
i_like_frog/main/__init__.py
i_like_frog/main/ilikefrog.py
i_like_frog/test/__init__.py
i_like_frog/test/test_ilikefrog.py
ILikeFrog-0.0.3.dist-info/METADATA
ILikeFrog-0.0.3.dist-info/WHEEL
ILikeFrog-0.0.3.dist-info/entry_points.txt
ILikeFrog-0.0.3.dist-info/top_level.txt
ILikeFrog-0.0.3.dist-info/RECORD
