Metadata-Version: 2.1
Name: ILikeFrog
Version: 0.0.3
Summary: Utility for converting to and from Frog-Talk
Home-page: https://github.com/Drakovek/ILikeFrog
Author: Drakovek
Author-email: DrakovekMail@gmail.com
License: UNKNOWN
Platform: UNKNOWN
Classifier: Programming Language :: Python :: 3
Classifier: License :: OSI Approved :: GNU General Public License v3 (GPLv3)
Classifier: Operating System :: OS Independent
Requires-Python: >=3.0
